PredDNAContam/__init__.py
PredDNAContam/model/Random_Forest_Contamination_Model.joblib
PredDNAContam/model/__init__.py
PredDNAContam/model/scaler.joblib
PredDNAContam/scripts/PredDNAcontam_BioSamples.py
PredDNAContam/scripts/__init__.py
PredDNAContam/scripts/config.txt
PredDNAContam/scripts/__pycache__/PredDNAcontam_BioSamples.cpython-38.pyc
PredDNAContam/scripts/__pycache__/__init__.cpython-38.pyc
PredDNAContam-0.1.dist-info/METADATA
PredDNAContam-0.1.dist-info/WHEEL
PredDNAContam-0.1.dist-info/entry_points.txt
PredDNAContam-0.1.dist-info/top_level.txt
PredDNAContam-0.1.dist-info/RECORD
