Metadata-Version: 2.1
Name: PredDNAContam
Version: 0.1
Summary: A Machine Learning Model to Estimate Within-Species DNA Contamination.
Home-page: https://github.com/razmo63/PredDNAContam
Author: Raziyeh Mohseni
Author-email: raziyeh.mohseni.y@gmail.com
Requires-Python: >=3.8, <3.9
Requires-Dist: pandas==1.4.4
Requires-Dist: numpy==1.19.5
Requires-Dist: scikit-learn==1.1.2
Requires-Dist: matplotlib==3.6.2
Requires-Dist: seaborn==0.12.2
Requires-Dist: joblib==1.4.2
